chroma_ops/__init__.py
chroma_ops/collection.py
chroma_ops/collection_snapshot.py
chroma_ops/constants.py
chroma_ops/db.py
chroma_ops/db_clean.py
chroma_ops/db_info.py
chroma_ops/fts.py
chroma_ops/hnsw.py
chroma_ops/main.py
chroma_ops/scripts/drop_fts.sql
chroma_ops/scripts/snapshot.sql
chroma_ops/utils.py
chroma_ops/wal.py
chroma_ops/wal_clean.py
chroma_ops/wal_commit.py
chroma_ops/wal_config.py
chroma_ops/wal_export.py
chroma_ops/wal_info.py
chromadb_ops-0.1.5.dist-info/LICENSE.md
chromadb_ops-0.1.5.dist-info/METADATA
chromadb_ops-0.1.5.dist-info/WHEEL
chromadb_ops-0.1.5.dist-info/entry_points.txt
chromadb_ops-0.1.5.dist-info/RECORD
