Metadata-Version: 2.3
Name: chromadb-ops
Version: 0.1.5
Summary: Maintenance CLI for Chroma AI-native database.
License: MIT
Author: Trayan Azarov
Author-email: trayan.azarov@amikos.tech
Requires-Python: >=3.9
Classifier: License :: OSI Approved :: MIT License
Classifier: Programming Language :: Python :: 3
Classifier: Programming Language :: Python :: 3.9
Classifier: Programming Language :: Python :: 3.10
Classifier: Programming Language :: Python :: 3.11
Classifier: Programming Language :: Python :: 3.12
Classifier: Programming Language :: Python :: 3.13
Provides-Extra: core
Requires-Dist: chroma-hnswlib (>=0.7.6,<0.8.0)
Requires-Dist: chromadb (==1.0.16) ; extra == "core"
Requires-Dist: typer[all] (>=0.9.0,<0.10.0)
Project-URL: Bug Tracker, https://github.com/amikos-tech/chromadb-ops/issues
Project-URL: Homepage, https://github.com/amikos-tech/chromadb-ops/
Project-URL: Source, https://github.com/amikos-tech/chromadb-ops/
